{
  "type": "Feature",
  "properties": {
    "gn:admin1_code":"0.0",
    "gn:asciiname":"Kaleva",
    "gn:country_code":"WF",
    "gn:dem":11,
    "gn:feature_class":"P",
    "gn:feature_code":"PPL",
    "gn:name":"Kaleva",
    "gn:population":0,
    "gn:timezone":"Pacific/Wallis",
    "iso:country":"WF",
    "name:ceb_x_preferred":[
        "Kaleva"
    ],
    "name:deu_x_preferred":[
        "Kaleva"
    ],
    "name:est_x_preferred":[
        "Kaleva"
    ],
    "name:fin_x_preferred":[
        "Kaleva"
    ],
    "name:fra_x_preferred":[
        "Kaleva"
    ],
    "name:nld_x_preferred":[
        "Kaleva"
    ],
    "name:por_x_preferred":[
        "Kaleva"
    ],
    "name:rus_x_preferred":[
        "\u041a\u0430\u043b\u0435\u0432\u0430"
    ],
    "name:swe_x_preferred":[
        "Kaleva"
    ],
    "wof:name":"Kaleva",
    "wof:placetype":"locality"
},
  "geometry": {"coordinates":[-176.1808,-13.24234],"type":"Point"}
}