{
  "type": "Feature",
  "properties": {
    "gn:admin1_code":"98613.0",
    "gn:asciiname":"Gamua",
    "gn:country_code":"WF",
    "gn:dem":8,
    "gn:feature_class":"P",
    "gn:feature_code":"PPL",
    "gn:name":"Gamua",
    "gn:population":0,
    "gn:timezone":"Pacific/Wallis",
    "iso:country":"WF",
    "wof:name":"Gamua",
    "wof:placetype":"locality"
},
  "geometry": {"coordinates":[-176.17813000000001,-13.24855],"type":"Point"}
}