{
  "type": "Feature",
  "properties": {
    "gn:admin1_code":"98613.0",
    "gn:asciiname":"Halamaitai",
    "gn:country_code":"WF",
    "gn:dem":48,
    "gn:feature_class":"P",
    "gn:feature_code":"PPL",
    "gn:name":"Halamaitai",
    "gn:population":0,
    "gn:timezone":"Pacific/Wallis",
    "iso:country":"WF",
    "wof:name":"Halamaitai",
    "wof:placetype":"locality"
},
  "geometry": {"coordinates":[-176.19045,-13.28184],"type":"Point"}
}