{
  "type": "Feature",
  "properties": {
    "gn:country":"WF",
    "gn:fcode":"PPL",
    "gn:pop":601,
    "iso:country":"WF",
    "name:deu_x_preferred":[
        "Vaitupu"
    ],
    "name:eng_x_preferred":[
        "Vaitupu"
    ],
    "name:fra_x_preferred":[
        "Vaitupu"
    ],
    "name:ita_x_preferred":[
        "Vaitupu"
    ],
    "name:nld_x_preferred":[
        "Vaitupu"
    ],
    "name:pol_x_preferred":[
        "Vaitupu"
    ],
    "name:swe_x_preferred":[
        "Vaitupu"
    ],
    "qs:name":"Vaitupu",
    "qs:photos_9r":0,
    "qs:photos_sr":0,
    "qs:pop_sr":"2",
    "wd:wordcount":2627,
    "wof:name":"Vaitupu",
    "wof:placetype":"locality",
    "wof:population":601
},
  "geometry": {"coordinates":[-176.15000000000001,-13.23333],"type":"Point"}
}