{
  "type": "Feature",
  "properties": {
    "gn:country":"WF",
    "gn:fcode":"PPL",
    "gn:population":601,
    "iso:country":"WF",
    "name:deu_x_preferred":[
        "Vaitupu"
    ],
    "name:eng_x_preferred":[
        "Vaitupu"
    ],
    "name:fra_x_preferred":[
        "Vaitupu"
    ],
    "name:ita_x_preferred":[
        "Vaitupu"
    ],
    "name:nld_x_preferred":[
        "Vaitupu"
    ],
    "name:pol_x_preferred":[
        "Vaitupu"
    ],
    "name:rus_x_preferred":[
        "\u0412\u0430\u0438\u0442\u0443\u043f\u0443"
    ],
    "name:swe_x_preferred":[
        "Vaitupu"
    ],
    "name:wls_x_preferred":[
        "Vaitupu"
    ],
    "name:zho_x_preferred":[
        "\u74e6\u4f0a\u56fe\u666e"
    ],
    "qs:name":"Vaitupu",
    "qs:photos_9r":0,
    "qs:photos_sr":0,
    "qs:pop_sr":"2",
    "wd:wordcount":2627,
    "wof:name":"Vaitupu",
    "wof:placetype":"locality",
    "wof:population":601
},
  "geometry": {"coordinates":[-176.15000000000001,-13.23333],"type":"Point"}
}