{
  "type": "Feature",
  "properties": {
    "gn:admin1_code":"98613.0",
    "gn:asciiname":"Makeke",
    "gn:country_code":"WF",
    "gn:dem":27,
    "gn:feature_class":"P",
    "gn:feature_code":"PPL",
    "gn:name":"Makeke",
    "gn:population":0,
    "gn:timezone":"Pacific/Wallis",
    "iso:country":"WF",
    "name:fra_x_preferred":[
        "Makeke"
    ],
    "wof:name":"Makeke",
    "wof:placetype":"locality"
},
  "geometry": {"coordinates":[-176.18898000000004,-13.30308],"type":"Point"}
}