{
  "type": "Feature",
  "properties": {
    "gn:admin1_code":"98613.0",
    "gn:asciiname":"Siaina",
    "gn:country_code":"WF",
    "gn:dem":7,
    "gn:feature_class":"P",
    "gn:feature_code":"PPL",
    "gn:name":"Siaina",
    "gn:population":0,
    "gn:timezone":"Pacific/Wallis",
    "iso:country":"WF",
    "name:fra_x_preferred":[
        "Siaina"
    ],
    "wof:name":"Siaina",
    "wof:placetype":"locality"
},
  "geometry": {"coordinates":[-176.18583999999996,-13.23144],"type":"Point"}
}